{
  "generatedAt": "2026-07-01T06:59:55.876Z",
  "source": "scripts/generate-site-stats.js",
  "note": "Measured on every run. Displayed counts are rounded DOWN so the public \"N+\" claim is always an under-statement. Do not hand-edit — run the script.",
  "tests": {
    "total": 5944,
    "passing": 5941,
    "failing": 0,
    "skipped": 0,
    "displayPassing": "5,900+"
  },
  "modules": {
    "total": 112,
    "green": 102,
    "scanned": 110,
    "displayGreen": "102/110",
    "greenSource": "carried",
    "greenMeasuredAt": null
  },
  "flywheel": {
    "totalFixAttempts": 2109,
    "claudeRatioPct": 71,
    "accuracyPct": 44.7,
    "recent7dFixAttempts": 2109
  }
}
